ai/__init__.py
ai/config.py
ai/core.py
ai/image.py
ai/logging.py
ai/model.py
ai/providers/base.py
ai/providers/google.py
ai/providers/openai.py
ai/tools.py
ai/types.py
ai/utils.py
python_ai_sdk-0.0.3.dist-info/LICENSE
python_ai_sdk-0.0.3.dist-info/METADATA
python_ai_sdk-0.0.3.dist-info/WHEEL
python_ai_sdk-0.0.3.dist-info/RECORD
