Metadata-Version: 2.3
Name: python-ai-sdk
Version: 0.0.3
Summary: A Python AI SDK inspired by the Vercel AI SDK with streaming support and multi-provider integration.
License: MIT
Keywords: ai,openai,google,streaming,sdk,llm
Author: David uche
Author-email: Daviduche176@gmail.com
Requires-Python: >=3.9,<4.0
Classifier: Development Status :: 3 - Alpha
Classifier: Intended Audience :: Developers
Classifier: License :: OSI Approved :: MIT License
Classifier: Programming Language :: Python :: 3
Classifier: Programming Language :: Python :: 3.9
Classifier: Programming Language :: Python :: 3.10
Classifier: Programming Language :: Python :: 3.11
Classifier: Programming Language :: Python :: 3.12
Classifier: Programming Language :: Python :: 3.13
Classifier: Topic :: Scientific/Engineering :: Artificial Intelligence
Classifier: Topic :: Software Development :: Libraries :: Python Modules
Provides-Extra: all
Provides-Extra: anthropic
Provides-Extra: fastapi
Requires-Dist: anthropic (>=0.25.0) ; extra == "anthropic" or extra == "all"
Requires-Dist: fastapi (>=0.100.0) ; extra == "fastapi" or extra == "all"
Requires-Dist: google-genai (>=1.0.0)
Requires-Dist: httpx (>=0.25.0)
Requires-Dist: openai (>=1.0.0)
Requires-Dist: pydantic (>=2.0.0)
Requires-Dist: requests (>=2.25.0)
Requires-Dist: uvicorn[standard] (>=0.20.0) ; extra == "fastapi" or extra == "all"
Project-URL: Documentation, https://github.com/Daviduche03/ai.py#readme
Project-URL: Homepage, https://github.com/Daviduche03/ai.py
Project-URL: Repository, https://github.com/Daviduche03/ai.py
